newgroundsdl/__init__.py
newgroundsdl-0.2.1.data/scripts/newgroundsdl
newgroundsdl-0.2.1.dist-info/METADATA
newgroundsdl-0.2.1.dist-info/RECORD
newgroundsdl-0.2.1.dist-info/WHEEL
newgroundsdl-0.2.1.dist-info/top_level.txt
